<PAMDataset>
  <SRS>GEOGCS["GCS_WGS_1984",DATUM["WGS_1984",SPHEROID["WGS_84",6378137.0,298.257223563,AUTHORITY["EPSG","7030"]],AUTHORITY["EPSG","6326"]],PRIMEM["Greenwich",0.0,AUTHORITY["EPSG","8901"]],UNIT["Degree",0.0174532925199433,AUTHORITY["EPSG","9102"]],AUTHORITY["EPSG","4326"]]</SRS>
  <Metadata domain="IMAGE_STRUCTURE">
    <MDI key="COMPRESSION">JPEG</MDI>
    <MDI key="INTERLEAVE">PIXEL</MDI>
    <MDI key="SOURCE_COLOR_SPACE">YCbCr</MDI>
  </Metadata>
  <Metadata>
    <MDI key="DataType">Generic</MDI>
  </Metadata>
  <Metadata domain="Esri">
    <MDI key="PyramidResamplingType">NEAREST</MDI>
  </Metadata>
  <PAMRasterBand band="1">
    <NoDataValue>2.56000000000000E+02</NoDataValue>
    <Histograms>
      <HistItem>
        <HistMin>-0.5</HistMin>
        <HistMax>255.5</HistMax>
        <BucketCount>256</BucketCount>
        <IncludeOutOfRange>1</IncludeOutOfRange>
        <Approximate>0</Approximate>
        <HistCounts>147|42|42|36|61|60|67|66|88|101|105|110|105|117|133|147|142|191|189|171|216|206|232|261|247|234|287|263|282|337|327|379|342|338|396|386|398|406|448|448|441|457|473|481|515|514|509|549|500|566|551|575|557|533|592|538|594|597|606|628|564|547|597|577|604|638|562|585|565|575|567|550|554|539|587|517|584|501|538|551|503|511|547|519|472|502|459|496|510|519|475|497|417|488|447|457|490|492|427|446|415|448|468|460|475|485|427|449|423|457|429|398|455|416|419|421|446|414|404|408|405|413|448|429|411|399|429|399|446|382|412|427|442|424|431|420|394|423|450|424|434|400|422|426|426|385|433|396|422|435|444|430|417|422|434|414|434|411|420|413|423|435|445|443|475|441|469|446|456|439|457|488|468|497|474|474|468|461|481|476|473|475|509|514|566|542|552|561|504|551|535|544|575|589|592|578|605|568|620|641|658|637|652|672|667|674|733|754|814|725|769|791|847|841|840|922|862|885|952|956|922|974|1029|1087|1085|1085|1168|1204|1251|1326|1409|1455|1584|1798|1896|1991|2200|2491|2863|3230|3716|4177|4822|5697|6629|7492|8362|9044|9805|10441|10642|10232|9434|7645|6653|13496</HistCounts>
      </HistItem>
    </Histograms>
    <Metadata domain="IMAGE_STRUCTURE">
      <MDI key="COMPRESSION">JPEG</MDI>
    </Metadata>
    <Metadata>
      <MDI key="BandName">Band_1</MDI>
      <MDI key="SourceBandIndex">0</MDI>
      <MDI key="STATISTICS_COVARIANCES">4963.240314434983,4126.370576553059,4676.359807392227</MDI>
      <MDI key="STATISTICS_EXCLUDEDVALUES"></MDI>
      <MDI key="STATISTICS_MAXIMUM">255</MDI>
      <MDI key="STATISTICS_MEAN">198.32646560669</MDI>
      <MDI key="STATISTICS_MINIMUM">0</MDI>
      <MDI key="STATISTICS_SKIPFACTORX">1</MDI>
      <MDI key="STATISTICS_SKIPFACTORY">1</MDI>
      <MDI key="STATISTICS_STDDEV">70.45026837731</MDI>
    </Metadata>
  </PAMRasterBand>
  <PAMRasterBand band="2">
    <NoDataValue>2.56000000000000E+02</NoDataValue>
    <Histograms>
      <HistItem>
        <HistMin>-0.5</HistMin>
        <HistMax>255.5</HistMax>
        <BucketCount>256</BucketCount>
        <IncludeOutOfRange>1</IncludeOutOfRange>
        <Approximate>0</Approximate>
        <HistCounts>264|48|45|55|47|58|73|48|58|51|45|51|53|64|59|44|55|58|44|54|48|57|59|45|55|47|64|57|72|52|45|59|53|62|61|66|72|64|87|68|82|80|79|95|97|107|112|130|137|133|160|155|152|175|215|217|226|238|268|293|320|350|404|403|414|428|410|465|494|523|525|559|566|578|609|583|620|652|674|702|717|750|760|750|770|783|767|804|760|783|752|842|819|811|788|806|759|825|761|809|773|788|798|745|792|704|680|745|681|693|672|654|656|665|636|635|627|633|641|598|605|588|611|580|571|545|592|522|577|502|545|516|522|537|520|547|520|510|479|511|469|504|467|469|481|454|475|468|491|485|479|436|465|491|507|502|469|464|503|442|470|472|494|453|477|432|467|441|482|484|465|471|502|456|509|475|515|498|470|499|455|498|527|506|508|509|535|520|506|540|564|509|543|483|599|576|552|567|629|573|613|652|615|640|621|656|614|665|673|669|751|828|775|790|829|866|956|956|1003|994|1108|1163|1215|1322|1399|1449|1559|1687|1865|2083|2189|2243|2562|2836|2916|3325|3528|3822|4198|4554|4996|5508|5973|6337|7001|7503|7821|8338|8665|8389|8541|8325|7625|6558|5312|7082</HistCounts>
      </HistItem>
    </Histograms>
    <Metadata domain="IMAGE_STRUCTURE">
      <MDI key="COMPRESSION">JPEG</MDI>
    </Metadata>
    <Metadata>
      <MDI key="BandName">Band_2</MDI>
      <MDI key="SourceBandIndex">1</MDI>
      <MDI key="STATISTICS_COVARIANCES">4126.370576553059,3938.809295767317,4385.1357729007</MDI>
      <MDI key="STATISTICS_EXCLUDEDVALUES"></MDI>
      <MDI key="STATISTICS_MAXIMUM">255</MDI>
      <MDI key="STATISTICS_MEAN">200.88912200928</MDI>
      <MDI key="STATISTICS_MINIMUM">0</MDI>
      <MDI key="STATISTICS_SKIPFACTORX">1</MDI>
      <MDI key="STATISTICS_SKIPFACTORY">1</MDI>
      <MDI key="STATISTICS_STDDEV">62.759933841324</MDI>
    </Metadata>
  </PAMRasterBand>
  <PAMRasterBand band="3">
    <NoDataValue>2.56000000000000E+02</NoDataValue>
    <Histograms>
      <HistItem>
        <HistMin>-0.5</HistMin>
        <HistMax>255.5</HistMax>
        <BucketCount>256</BucketCount>
        <IncludeOutOfRange>1</IncludeOutOfRange>
        <Approximate>0</Approximate>
        <HistCounts>731|72|66|80|75|78|74|69|74|73|80|74|84|99|116|84|116|102|121|134|142|135|170|137|155|184|182|191|204|236|220|260|264|242|263|310|345|302|375|391|348|411|393|426|406|468|495|543|544|538|529|555|582|577|606|633|607|645|670|678|685|719|727|760|742|696|705|738|710|710|704|711|720|686|682|706|661|720|646|656|674|624|612|655|642|648|612|644|593|587|572|596|603|580|572|559|528|571|526|520|540|520|540|521|505|497|531|494|519|501|485|534|466|500|491|430|483|474|484|452|463|462|460|463|415|442|458|456|484|451|426|458|455|455|417|426|440|433|467|453|450|446|432|426|460|453|434|454|417|409|436|435|418|444|438|440|450|434|416|447|445|427|472|444|417|463|449|455|459|472|496|476|491|480|463|495|488|487|464|495|467|502|490|497|505|532|505|505|498|498|582|538|580|542|591|629|553|593|591|583|644|619|643|653|678|664|688|729|737|726|751|789|823|827|915|928|995|1018|1046|1126|1137|1205|1255|1303|1345|1463|1571|1737|1809|1972|2184|2335|2544|2758|2978|3318|3749|4074|4463|5043|5468|6040|6476|7081|7510|7979|8033|8362|8343|8125|7708|6949|5410|5200|2587|5056</HistCounts>
      </HistItem>
    </Histograms>
    <Metadata domain="IMAGE_STRUCTURE">
      <MDI key="COMPRESSION">JPEG</MDI>
    </Metadata>
    <Metadata>
      <MDI key="BandName">Band_3</MDI>
      <MDI key="SourceBandIndex">2</MDI>
      <MDI key="STATISTICS_COVARIANCES">4676.359807392227,4385.1357729007,4923.004122863597</MDI>
      <MDI key="STATISTICS_EXCLUDEDVALUES"></MDI>
      <MDI key="STATISTICS_MAXIMUM">255</MDI>
      <MDI key="STATISTICS_MEAN">193.68320083618</MDI>
      <MDI key="STATISTICS_MINIMUM">0</MDI>
      <MDI key="STATISTICS_SKIPFACTORX">1</MDI>
      <MDI key="STATISTICS_SKIPFACTORY">1</MDI>
      <MDI key="STATISTICS_STDDEV">70.164122761306</MDI>
    </Metadata>
  </PAMRasterBand>
</PAMDataset>
