<PAMDataset>
  <SRS>GEOGCS["GCS_WGS_1984",DATUM["WGS_1984",SPHEROID["WGS_84",6378137.0,298.257223563,AUTHORITY["EPSG","7030"]],AUTHORITY["EPSG","6326"]],PRIMEM["Greenwich",0.0,AUTHORITY["EPSG","8901"]],UNIT["Degree",0.0174532925199433,AUTHORITY["EPSG","9102"]],AUTHORITY["EPSG","4326"]]</SRS>
  <Metadata domain="IMAGE_STRUCTURE">
    <MDI key="COMPRESSION">JPEG</MDI>
    <MDI key="INTERLEAVE">PIXEL</MDI>
    <MDI key="SOURCE_COLOR_SPACE">YCbCr</MDI>
  </Metadata>
  <Metadata>
    <MDI key="DataType">Generic</MDI>
  </Metadata>
  <Metadata domain="Esri">
    <MDI key="PyramidResamplingType">NEAREST</MDI>
  </Metadata>
  <PAMRasterBand band="1">
    <NoDataValue>2.56000000000000E+02</NoDataValue>
    <Histograms>
      <HistItem>
        <HistMin>-0.5</HistMin>
        <HistMax>255.5</HistMax>
        <BucketCount>256</BucketCount>
        <IncludeOutOfRange>1</IncludeOutOfRange>
        <Approximate>0</Approximate>
        <HistCounts>25|3|8|13|16|15|14|18|25|26|20|34|43|39|49|56|57|52|62|59|66|59|82|83|98|105|101|111|150|130|149|154|159|154|182|185|201|190|212|206|217|232|254|232|254|286|287|285|302|324|313|320|356|337|347|314|358|362|387|354|346|369|377|376|362|401|375|420|374|364|398|398|395|402|414|448|410|400|421|414|375|393|420|408|391|385|382|371|356|385|341|379|336|363|346|365|371|373|383|346|381|368|325|391|350|399|364|323|361|361|318|339|366|343|344|325|360|327|326|319|317|321|344|357|322|357|347|369|329|367|349|369|354|370|332|359|377|367|360|352|357|346|386|411|352|380|397|360|379|376|400|378|374|387|388|403|414|409|444|412|408|375|396|427|401|440|455|406|425|443|427|456|413|434|469|436|480|429|443|449|460|448|483|442|447|472|494|538|481|483|504|516|530|536|539|534|529|545|559|571|608|608|566|625|599|643|616|655|690|638|670|687|684|706|728|769|817|820|865|818|872|905|914|1000|1009|1089|1153|1172|1223|1299|1313|1425|1559|1649|1680|1844|2055|2156|2489|2729|3195|3545|4174|4924|5688|6926|8138|9538|11242|12774|14008|14229|14118|11702|9641|19605</HistCounts>
      </HistItem>
    </Histograms>
    <Metadata domain="IMAGE_STRUCTURE">
      <MDI key="COMPRESSION">JPEG</MDI>
    </Metadata>
    <Metadata>
      <MDI key="BandName">Band_1</MDI>
      <MDI key="SourceBandIndex">0</MDI>
      <MDI key="STATISTICS_COVARIANCES">3628.949404412385,3573.580232005337,3844.972231961921</MDI>
      <MDI key="STATISTICS_EXCLUDEDVALUES"></MDI>
      <MDI key="STATISTICS_MAXIMUM">255</MDI>
      <MDI key="STATISTICS_MEAN">213.06326675415</MDI>
      <MDI key="STATISTICS_MINIMUM">0</MDI>
      <MDI key="STATISTICS_SKIPFACTORX">1</MDI>
      <MDI key="STATISTICS_SKIPFACTORY">1</MDI>
      <MDI key="STATISTICS_STDDEV">60.240761983995</MDI>
    </Metadata>
  </PAMRasterBand>
  <PAMRasterBand band="2">
    <NoDataValue>2.56000000000000E+02</NoDataValue>
    <Histograms>
      <HistItem>
        <HistMin>-0.5</HistMin>
        <HistMax>255.5</HistMax>
        <BucketCount>256</BucketCount>
        <IncludeOutOfRange>1</IncludeOutOfRange>
        <Approximate>0</Approximate>
        <HistCounts>3|1|3|9|8|10|7|10|11|19|19|22|19|30|34|30|37|56|45|58|56|55|79|59|56|84|82|87|89|118|103|142|129|149|151|154|170|186|221|192|238|227|256|220|264|259|275|305|306|291|344|335|329|362|385|385|361|349|407|399|417|390|403|396|425|413|379|406|395|470|455|406|429|446|437|393|454|415|443|416|411|398|389|432|405|401|400|419|388|374|365|392|372|351|372|348|359|410|348|383|431|380|385|347|390|326|357|362|352|333|344|396|350|354|344|353|361|336|359|363|341|356|347|333|344|360|361|362|324|361|387|378|351|352|319|391|362|385|361|388|365|379|380|374|446|409|405|417|369|408|395|426|373|394|413|399|436|405|443|408|441|411|406|401|429|459|469|444|454|443|439|414|422|456|439|517|485|496|467|456|471|467|474|498|495|465|507|514|563|543|520|526|530|579|578|567|583|638|592|579|619|628|639|626|647|651|677|699|687|719|732|741|825|763|841|910|919|936|980|989|1103|1103|1107|1151|1275|1379|1371|1517|1660|1733|1791|1961|2131|2377|2496|2744|3100|3226|3735|4186|4675|5148|5625|6638|7071|8055|8944|9811|10276|10979|11255|11313|10824|9698|8232|9964</HistCounts>
      </HistItem>
    </Histograms>
    <Metadata domain="IMAGE_STRUCTURE">
      <MDI key="COMPRESSION">JPEG</MDI>
    </Metadata>
    <Metadata>
      <MDI key="BandName">Band_2</MDI>
      <MDI key="SourceBandIndex">1</MDI>
      <MDI key="STATISTICS_COVARIANCES">3573.580232005337,3538.062646141235,3806.562679169799</MDI>
      <MDI key="STATISTICS_EXCLUDEDVALUES"></MDI>
      <MDI key="STATISTICS_MAXIMUM">255</MDI>
      <MDI key="STATISTICS_MEAN">210.94243240357</MDI>
      <MDI key="STATISTICS_MINIMUM">0</MDI>
      <MDI key="STATISTICS_SKIPFACTORX">1</MDI>
      <MDI key="STATISTICS_SKIPFACTORY">1</MDI>
      <MDI key="STATISTICS_STDDEV">59.481616035051</MDI>
    </Metadata>
  </PAMRasterBand>
  <PAMRasterBand band="3">
    <NoDataValue>2.56000000000000E+02</NoDataValue>
    <Histograms>
      <HistItem>
        <HistMin>-0.5</HistMin>
        <HistMax>255.5</HistMax>
        <BucketCount>256</BucketCount>
        <IncludeOutOfRange>1</IncludeOutOfRange>
        <Approximate>0</Approximate>
        <HistCounts>724|98|86|111|113|134|141|133|144|161|163|166|179|181|219|216|229|251|242|241|254|253|263|283|287|295|299|315|306|322|328|307|343|326|337|333|362|377|398|394|369|379|373|396|373|393|362|395|407|394|405|370|373|383|348|357|338|389|389|351|399|335|358|378|316|358|348|368|363|359|330|365|344|338|323|367|351|347|348|329|363|335|316|317|351|335|340|294|344|328|359|321|333|317|320|308|343|323|335|332|332|344|331|351|292|332|321|316|304|364|360|336|356|353|293|359|351|357|359|306|306|366|364|351|389|432|361|373|373|354|392|378|394|377|375|381|365|395|369|431|362|395|358|431|407|405|420|403|385|429|407|405|404|398|432|422|457|440|408|478|449|407|471|446|427|444|442|497|453|480|468|460|504|500|544|505|510|536|567|528|537|555|533|592|556|573|586|572|567|590|625|618|631|656|690|652|701|659|739|737|755|822|862|868|844|866|917|941|1020|1014|1037|1106|1153|1197|1292|1340|1400|1440|1527|1632|1728|1941|2072|2240|2296|2436|2745|3112|3437|3568|4109|4469|4774|5313|5670|6195|6693|6891|7329|7496|7581|7668|7515|7556|7300|6860|6935|5878|5772|4251|4052|2970|1668|1707|598|1294</HistCounts>
      </HistItem>
    </Histograms>
    <Metadata domain="IMAGE_STRUCTURE">
      <MDI key="COMPRESSION">JPEG</MDI>
    </Metadata>
    <Metadata>
      <MDI key="BandName">Band_3</MDI>
      <MDI key="SourceBandIndex">2</MDI>
      <MDI key="STATISTICS_COVARIANCES">3844.972231961921,3806.562679169799,4122.803746293471</MDI>
      <MDI key="STATISTICS_EXCLUDEDVALUES"></MDI>
      <MDI key="STATISTICS_MAXIMUM">255</MDI>
      <MDI key="STATISTICS_MEAN">199.8840637207</MDI>
      <MDI key="STATISTICS_MINIMUM">0</MDI>
      <MDI key="STATISTICS_SKIPFACTORX">1</MDI>
      <MDI key="STATISTICS_SKIPFACTORY">1</MDI>
      <MDI key="STATISTICS_STDDEV">64.209062804977</MDI>
    </Metadata>
  </PAMRasterBand>
</PAMDataset>
