<PAMDataset>
  <SRS>GEOGCS["GCS_WGS_1984",DATUM["WGS_1984",SPHEROID["WGS_84",6378137.0,298.257223563,AUTHORITY["EPSG","7030"]],AUTHORITY["EPSG","6326"]],PRIMEM["Greenwich",0.0,AUTHORITY["EPSG","8901"]],UNIT["Degree",0.0174532925199433,AUTHORITY["EPSG","9102"]],AUTHORITY["EPSG","4326"]]</SRS>
  <Metadata domain="IMAGE_STRUCTURE">
    <MDI key="COMPRESSION">JPEG</MDI>
    <MDI key="INTERLEAVE">PIXEL</MDI>
    <MDI key="SOURCE_COLOR_SPACE">YCbCr</MDI>
  </Metadata>
  <Metadata>
    <MDI key="DataType">Generic</MDI>
  </Metadata>
  <Metadata domain="Esri">
    <MDI key="PyramidResamplingType">NEAREST</MDI>
  </Metadata>
  <PAMRasterBand band="1">
    <NoDataValue>2.56000000000000E+02</NoDataValue>
    <Histograms>
      <HistItem>
        <HistMin>-0.5</HistMin>
        <HistMax>255.5</HistMax>
        <BucketCount>256</BucketCount>
        <IncludeOutOfRange>1</IncludeOutOfRange>
        <Approximate>0</Approximate>
        <HistCounts>20|6|9|9|9|10|10|17|19|21|32|22|22|46|36|47|61|56|72|68|63|73|98|108|105|105|109|128|147|123|192|152|174|215|175|229|229|252|253|243|270|262|307|309|329|361|358|377|377|394|405|410|429|411|445|407|484|466|461|487|490|499|489|483|518|500|518|526|504|504|481|518|505|519|467|501|501|508|469|487|475|487|511|466|498|506|463|474|477|473|449|485|474|477|458|473|444|436|464|469|431|391|427|409|456|399|457|418|421|391|430|420|430|430|420|403|413|415|417|414|456|405|446|407|382|450|401|435|408|437|411|439|437|398|398|402|412|412|456|413|402|474|424|438|440|420|412|428|410|440|456|406|414|396|476|459|467|455|450|447|451|451|469|449|457|498|455|490|467|483|451|506|468|471|467|487|495|499|478|474|536|490|539|510|531|504|606|599|550|603|569|519|580|631|607|591|605|577|621|637|632|665|624|685|670|691|746|738|782|738|771|759|831|809|843|863|873|887|975|964|983|1012|1069|1163|1152|1200|1172|1305|1444|1400|1558|1532|1625|1699|1851|1943|2158|2166|2439|2678|2930|3511|3961|4513|5315|6106|7068|8490|9583|11101|11906|12505|11596|10370|8440|20312</HistCounts>
      </HistItem>
    </Histograms>
    <Metadata domain="IMAGE_STRUCTURE">
      <MDI key="COMPRESSION">JPEG</MDI>
    </Metadata>
    <Metadata>
      <MDI key="BandName">Band_1</MDI>
      <MDI key="SourceBandIndex">0</MDI>
      <MDI key="STATISTICS_COVARIANCES">4115.65949794942,4051.471996107187,4367.08908602758</MDI>
      <MDI key="STATISTICS_EXCLUDEDVALUES"></MDI>
      <MDI key="STATISTICS_MAXIMUM">255</MDI>
      <MDI key="STATISTICS_MEAN">206.14221954346</MDI>
      <MDI key="STATISTICS_MINIMUM">0</MDI>
      <MDI key="STATISTICS_SKIPFACTORX">1</MDI>
      <MDI key="STATISTICS_SKIPFACTORY">1</MDI>
      <MDI key="STATISTICS_STDDEV">64.1534059731</MDI>
    </Metadata>
  </PAMRasterBand>
  <PAMRasterBand band="2">
    <NoDataValue>2.56000000000000E+02</NoDataValue>
    <Histograms>
      <HistItem>
        <HistMin>-0.5</HistMin>
        <HistMax>255.5</HistMax>
        <BucketCount>256</BucketCount>
        <IncludeOutOfRange>1</IncludeOutOfRange>
        <Approximate>0</Approximate>
        <HistCounts>440|82|100|95|104|102|89|78|82|90|91|76|79|96|92|80|91|91|114|101|106|120|99|104|141|140|160|151|168|175|191|194|219|199|215|260|253|282|281|316|301|325|345|361|353|362|379|376|420|417|462|462|466|488|501|522|518|522|556|530|546|537|560|588|582|566|562|555|605|593|562|525|530|555|559|582|546|551|514|548|558|539|554|524|591|518|479|542|504|502|502|479|491|444|497|450|513|507|467|463|475|434|443|433|418|477|447|436|428|397|454|416|436|422|445|463|432|428|385|443|463|455|430|425|401|427|433|407|433|405|404|408|402|415|437|415|445|463|488|407|442|453|435|420|436|452|399|467|438|418|452|412|456|423|451|447|474|442|463|463|449|460|497|450|444|479|467|487|444|450|469|487|490|433|520|459|525|492|512|514|479|545|560|539|531|547|527|605|541|561|562|567|557|544|569|628|628|655|669|645|661|654|644|721|710|740|728|711|757|769|818|803|840|845|919|930|1018|1023|1059|1179|1147|1269|1302|1362|1462|1494|1615|1675|1820|1942|1990|2104|2248|2485|2697|2868|3244|3531|3873|4285|4873|5268|5768|6342|7035|7767|8618|9033|9539|9774|9639|9132|8316|6584|4956|5550</HistCounts>
      </HistItem>
    </Histograms>
    <Metadata domain="IMAGE_STRUCTURE">
      <MDI key="COMPRESSION">JPEG</MDI>
    </Metadata>
    <Metadata>
      <MDI key="BandName">Band_2</MDI>
      <MDI key="SourceBandIndex">1</MDI>
      <MDI key="STATISTICS_COVARIANCES">4051.471996107187,4444.284505519052,4752.610988696165</MDI>
      <MDI key="STATISTICS_EXCLUDEDVALUES"></MDI>
      <MDI key="STATISTICS_MAXIMUM">255</MDI>
      <MDI key="STATISTICS_MEAN">200.20882797241</MDI>
      <MDI key="STATISTICS_MINIMUM">0</MDI>
      <MDI key="STATISTICS_SKIPFACTORX">1</MDI>
      <MDI key="STATISTICS_SKIPFACTORY">1</MDI>
      <MDI key="STATISTICS_STDDEV">66.665467113934</MDI>
    </Metadata>
  </PAMRasterBand>
  <PAMRasterBand band="3">
    <NoDataValue>2.56000000000000E+02</NoDataValue>
    <Histograms>
      <HistItem>
        <HistMin>-0.5</HistMin>
        <HistMax>255.5</HistMax>
        <BucketCount>256</BucketCount>
        <IncludeOutOfRange>1</IncludeOutOfRange>
        <Approximate>0</Approximate>
        <HistCounts>1625|209|182|240|247|280|225|244|261|281|279|304|315|320|318|359|346|413|362|356|378|366|409|416|477|440|451|435|462|440|489|442|449|486|506|502|496|525|543|501|491|514|474|527|542|534|480|542|491|530|519|512|503|486|499|484|474|500|507|489|448|452|474|475|446|444|467|408|441|438|428|438|440|435|414|412|422|436|444|441|420|443|418|427|421|451|393|416|397|420|401|453|356|404|371|396|404|408|394|389|397|403|385|397|392|417|406|425|399|367|438|389|415|378|416|372|416|415|402|367|416|392|424|417|417|429|415|400|417|423|396|441|428|412|387|419|414|427|433|431|395|404|425|464|436|471|413|468|425|426|401|453|486|464|466|478|449|432|446|466|463|451|468|501|505|477|477|471|503|521|484|504|547|525|516|507|547|589|536|565|521|538|608|571|554|610|594|626|625|669|663|668|648|664|686|715|706|733|752|774|761|813|834|805|851|894|913|968|1027|1080|1107|1194|1092|1205|1282|1337|1489|1448|1479|1642|1731|1812|1934|2053|2343|2438|2595|2823|3128|3361|3660|4075|4521|5038|5413|5904|6352|6978|7279|7661|7604|7737|7780|7608|7137|6338|5981|4735|4223|2700|2252|1388|598|517|154|326</HistCounts>
      </HistItem>
    </Histograms>
    <Metadata domain="IMAGE_STRUCTURE">
      <MDI key="COMPRESSION">JPEG</MDI>
    </Metadata>
    <Metadata>
      <MDI key="BandName">Band_3</MDI>
      <MDI key="SourceBandIndex">2</MDI>
      <MDI key="STATISTICS_COVARIANCES">4367.08908602758,4752.610988696165,5118.977444785377</MDI>
      <MDI key="STATISTICS_EXCLUDEDVALUES"></MDI>
      <MDI key="STATISTICS_MAXIMUM">255</MDI>
      <MDI key="STATISTICS_MEAN">189.00423049927</MDI>
      <MDI key="STATISTICS_MINIMUM">0</MDI>
      <MDI key="STATISTICS_SKIPFACTORX">1</MDI>
      <MDI key="STATISTICS_SKIPFACTORY">1</MDI>
      <MDI key="STATISTICS_STDDEV">71.547029601412</MDI>
    </Metadata>
  </PAMRasterBand>
</PAMDataset>
