<PAMDataset>
  <SRS>GEOGCS["GCS_WGS_1984",DATUM["WGS_1984",SPHEROID["WGS_84",6378137.0,298.257223563,AUTHORITY["EPSG","7030"]],AUTHORITY["EPSG","6326"]],PRIMEM["Greenwich",0.0,AUTHORITY["EPSG","8901"]],UNIT["Degree",0.0174532925199433,AUTHORITY["EPSG","9102"]],AUTHORITY["EPSG","4326"]]</SRS>
  <Metadata domain="IMAGE_STRUCTURE">
    <MDI key="COMPRESSION">JPEG</MDI>
    <MDI key="INTERLEAVE">PIXEL</MDI>
    <MDI key="SOURCE_COLOR_SPACE">YCbCr</MDI>
  </Metadata>
  <Metadata>
    <MDI key="DataType">Generic</MDI>
  </Metadata>
  <Metadata domain="Esri">
    <MDI key="PyramidResamplingType">NEAREST</MDI>
  </Metadata>
  <PAMRasterBand band="1">
    <NoDataValue>2.56000000000000E+02</NoDataValue>
    <Histograms>
      <HistItem>
        <HistMin>-0.5</HistMin>
        <HistMax>255.5</HistMax>
        <BucketCount>256</BucketCount>
        <IncludeOutOfRange>1</IncludeOutOfRange>
        <Approximate>0</Approximate>
        <HistCounts>406|67|84|108|109|140|166|153|154|167|174|190|219|237|230|268|248|264|280|301|316|338|338|345|350|336|392|351|372|385|424|378|379|388|424|419|403|433|454|423|444|495|415|424|420|416|415|488|421|431|430|451|416|467|439|450|433|437|421|420|456|401|440|418|378|397|431|392|448|384|395|369|403|355|354|383|397|386|368|341|351|354|368|338|340|331|314|328|339|343|356|327|310|298|297|316|313|312|318|286|328|314|295|294|280|280|275|276|300|311|296|276|301|289|280|284|271|279|270|294|263|271|300|237|265|297|279|242|263|256|282|247|296|272|256|301|255|289|256|256|258|254|270|278|288|273|264|268|244|303|293|283|264|275|277|264|259|277|289|260|248|284|282|270|291|273|291|306|286|302|310|279|278|319|356|339|331|369|335|327|309|360|348|325|344|377|385|358|353|378|384|429|388|404|428|417|419|406|437|430|431|444|432|429|491|451|482|456|485|511|510|499|565|551|584|554|634|573|651|594|633|663|685|708|718|741|723|761|817|850|877|929|983|1068|1129|1185|1411|1474|1761|2120|2694|3251|4163|5361|6926|8601|10768|13271|16064|18252|19159|17349|14637|9820|8111|8001</HistCounts>
      </HistItem>
    </Histograms>
    <Metadata domain="IMAGE_STRUCTURE">
      <MDI key="COMPRESSION">JPEG</MDI>
    </Metadata>
    <Metadata>
      <MDI key="BandName">Band_1</MDI>
      <MDI key="SourceBandIndex">0</MDI>
      <MDI key="STATISTICS_COVARIANCES">4858.633296864022,4116.944394356733,4621.187839866603</MDI>
      <MDI key="STATISTICS_EXCLUDEDVALUES"></MDI>
      <MDI key="STATISTICS_MAXIMUM">255</MDI>
      <MDI key="STATISTICS_MEAN">208.79846191406</MDI>
      <MDI key="STATISTICS_MINIMUM">0</MDI>
      <MDI key="STATISTICS_SKIPFACTORX">1</MDI>
      <MDI key="STATISTICS_SKIPFACTORY">1</MDI>
      <MDI key="STATISTICS_STDDEV">69.703897286049</MDI>
    </Metadata>
  </PAMRasterBand>
  <PAMRasterBand band="2">
    <NoDataValue>2.56000000000000E+02</NoDataValue>
    <Histograms>
      <HistItem>
        <HistMin>-0.5</HistMin>
        <HistMax>255.5</HistMax>
        <BucketCount>256</BucketCount>
        <IncludeOutOfRange>1</IncludeOutOfRange>
        <Approximate>0</Approximate>
        <HistCounts>213|48|39|46|55|53|49|61|43|42|62|43|41|54|39|55|44|48|42|40|41|40|54|46|36|42|39|48|57|54|57|58|56|67|83|89|100|92|87|113|133|136|156|165|163|184|206|205|242|270|269|273|319|294|330|314|390|419|412|454|434|439|461|444|490|511|501|533|508|555|585|613|552|559|556|551|571|539|602|556|560|526|577|574|553|540|544|554|573|518|540|543|531|544|514|552|524|504|536|544|480|460|493|471|476|456|501|438|459|426|430|433|441|431|418|398|417|414|380|371|373|377|332|362|375|352|337|343|327|364|341|350|349|318|351|335|338|296|319|296|317|295|327|326|311|310|294|333|312|326|316|289|268|300|287|305|332|303|304|292|288|289|301|293|290|313|286|303|334|269|312|302|311|280|293|303|328|344|339|288|325|323|321|360|300|315|325|324|352|347|353|318|368|376|361|340|369|360|373|378|392|372|365|411|449|438|394|444|446|404|475|474|456|493|468|527|489|502|523|610|613|614|632|680|673|727|750|861|820|907|933|1050|1104|1198|1378|1448|1594|1788|2139|2317|2792|3259|3795|4506|5482|6418|7640|9071|10981|12689|14569|16892|18001|17759|14960|18122</HistCounts>
      </HistItem>
    </Histograms>
    <Metadata domain="IMAGE_STRUCTURE">
      <MDI key="COMPRESSION">JPEG</MDI>
    </Metadata>
    <Metadata>
      <MDI key="BandName">Band_2</MDI>
      <MDI key="SourceBandIndex">1</MDI>
      <MDI key="STATISTICS_COVARIANCES">4116.944394356733,3940.52346084181,4353.933050663534</MDI>
      <MDI key="STATISTICS_EXCLUDEDVALUES"></MDI>
      <MDI key="STATISTICS_MAXIMUM">255</MDI>
      <MDI key="STATISTICS_MEAN">213.30597686767</MDI>
      <MDI key="STATISTICS_MINIMUM">0</MDI>
      <MDI key="STATISTICS_SKIPFACTORX">1</MDI>
      <MDI key="STATISTICS_SKIPFACTORY">1</MDI>
      <MDI key="STATISTICS_STDDEV">62.773588879734</MDI>
    </Metadata>
  </PAMRasterBand>
  <PAMRasterBand band="3">
    <NoDataValue>2.56000000000000E+02</NoDataValue>
    <Histograms>
      <HistItem>
        <HistMin>-0.5</HistMin>
        <HistMax>255.5</HistMax>
        <BucketCount>256</BucketCount>
        <IncludeOutOfRange>1</IncludeOutOfRange>
        <Approximate>0</Approximate>
        <HistCounts>560|60|85|86|81|71|85|88|96|108|117|125|132|143|141|154|159|171|183|188|189|226|202|204|236|241|253|241|291|279|279|291|311|358|326|308|389|353|345|361|349|399|377|426|490|430|475|475|481|525|529|515|497|511|534|550|496|553|558|536|572|534|568|550|537|541|520|509|508|518|511|501|485|481|474|487|434|422|452|461|469|459|432|449|406|403|376|415|380|422|418|392|396|392|369|367|348|362|354|355|349|325|348|340|352|341|354|331|328|290|305|311|319|293|311|338|296|329|328|323|327|289|318|284|286|329|270|295|299|280|290|268|262|302|280|286|287|288|261|271|298|294|299|288|287|307|303|285|277|265|271|285|307|270|301|278|286|271|283|270|258|260|283|267|261|295|317|322|304|274|287|307|273|309|304|314|308|319|320|347|349|333|305|315|338|318|353|386|334|366|344|365|346|367|399|406|387|382|390|347|358|350|445|416|417|427|423|477|454|475|461|477|443|508|524|550|554|564|594|607|604|633|695|743|755|761|826|832|838|928|930|1020|1100|1206|1276|1444|1618|1826|2095|2423|2800|3307|4105|4790|5838|6976|8102|9787|11345|13481|15256|16885|16639|15678|11281|16479</HistCounts>
      </HistItem>
    </Histograms>
    <Metadata domain="IMAGE_STRUCTURE">
      <MDI key="COMPRESSION">JPEG</MDI>
    </Metadata>
    <Metadata>
      <MDI key="BandName">Band_3</MDI>
      <MDI key="SourceBandIndex">2</MDI>
      <MDI key="STATISTICS_COVARIANCES">4621.187839866603,4353.933050663534,4842.290885296781</MDI>
      <MDI key="STATISTICS_EXCLUDEDVALUES"></MDI>
      <MDI key="STATISTICS_MAXIMUM">255</MDI>
      <MDI key="STATISTICS_MEAN">208.34401321411</MDI>
      <MDI key="STATISTICS_MINIMUM">0</MDI>
      <MDI key="STATISTICS_SKIPFACTORX">1</MDI>
      <MDI key="STATISTICS_SKIPFACTORY">1</MDI>
      <MDI key="STATISTICS_STDDEV">69.586571156343</MDI>
    </Metadata>
  </PAMRasterBand>
</PAMDataset>
