<PAMDataset>
  <SRS>GEOGCS["GCS_WGS_1984",DATUM["WGS_1984",SPHEROID["WGS_84",6378137.0,298.257223563,AUTHORITY["EPSG","7030"]],AUTHORITY["EPSG","6326"]],PRIMEM["Greenwich",0.0,AUTHORITY["EPSG","8901"]],UNIT["Degree",0.0174532925199433,AUTHORITY["EPSG","9102"]],AUTHORITY["EPSG","4326"]]</SRS>
  <Metadata domain="IMAGE_STRUCTURE">
    <MDI key="COMPRESSION">JPEG</MDI>
    <MDI key="INTERLEAVE">PIXEL</MDI>
    <MDI key="SOURCE_COLOR_SPACE">YCbCr</MDI>
  </Metadata>
  <Metadata>
    <MDI key="DataType">Generic</MDI>
  </Metadata>
  <Metadata domain="Esri">
    <MDI key="PyramidResamplingType">NEAREST</MDI>
  </Metadata>
  <PAMRasterBand band="1">
    <NoDataValue>2.56000000000000E+02</NoDataValue>
    <Histograms>
      <HistItem>
        <HistMin>-0.5</HistMin>
        <HistMax>255.5</HistMax>
        <BucketCount>256</BucketCount>
        <IncludeOutOfRange>1</IncludeOutOfRange>
        <Approximate>0</Approximate>
        <HistCounts>94|21|21|32|46|34|52|63|66|79|95|98|112|124|127|142|137|128|154|161|192|181|181|222|213|219|226|249|252|290|254|276|279|282|324|289|313|313|320|343|319|339|343|349|352|396|334|342|347|382|376|390|365|369|384|379|370|329|365|324|403|380|340|384|345|370|369|386|367|353|378|363|337|391|350|373|331|374|352|342|351|359|331|327|348|343|320|346|338|347|333|335|330|323|292|337|352|332|338|342|319|318|298|363|337|335|357|316|346|313|324|376|350|344|314|333|340|319|331|325|352|326|348|323|341|345|300|364|328|386|323|328|340|336|346|318|343|318|347|369|318|308|395|334|356|403|353|320|371|350|366|387|390|373|365|355|382|409|382|404|407|398|404|385|394|424|421|436|423|440|411|431|419|440|444|428|461|500|465|489|491|455|473|528|489|510|477|590|574|570|511|582|568|599|592|641|664|644|669|668|667|685|748|683|724|763|786|742|747|795|790|829|813|873|858|903|889|968|961|1044|1028|1092|1116|1106|1248|1251|1262|1247|1295|1369|1543|1422|1625|1766|1886|2050|2266|2562|2956|3453|3809|4508|5210|6142|7031|8091|8955|10061|10858|11146|11142|10999|10111|8785|7513|19127</HistCounts>
      </HistItem>
    </Histograms>
    <Metadata domain="IMAGE_STRUCTURE">
      <MDI key="COMPRESSION">JPEG</MDI>
    </Metadata>
    <Metadata>
      <MDI key="BandName">Band_1</MDI>
      <MDI key="SourceBandIndex">0</MDI>
      <MDI key="STATISTICS_COVARIANCES">4039.195159398848,3360.734593814732,3755.224683021293</MDI>
      <MDI key="STATISTICS_EXCLUDEDVALUES"></MDI>
      <MDI key="STATISTICS_MAXIMUM">255</MDI>
      <MDI key="STATISTICS_MEAN">209.24887847901</MDI>
      <MDI key="STATISTICS_MINIMUM">0</MDI>
      <MDI key="STATISTICS_SKIPFACTORX">1</MDI>
      <MDI key="STATISTICS_SKIPFACTORY">1</MDI>
      <MDI key="STATISTICS_STDDEV">63.554662766778</MDI>
    </Metadata>
  </PAMRasterBand>
  <PAMRasterBand band="2">
    <NoDataValue>2.56000000000000E+02</NoDataValue>
    <Histograms>
      <HistItem>
        <HistMin>-0.5</HistMin>
        <HistMax>255.5</HistMax>
        <BucketCount>256</BucketCount>
        <IncludeOutOfRange>1</IncludeOutOfRange>
        <Approximate>0</Approximate>
        <HistCounts>330|65|56|51|75|59|66|53|66|74|60|74|52|59|56|56|46|48|51|50|45|52|50|42|51|33|59|44|46|48|54|45|55|43|60|60|48|62|62|59|75|106|96|84|118|117|118|149|167|157|188|193|242|281|255|288|340|328|382|362|397|407|468|444|460|455|486|479|510|463|496|519|521|519|549|543|502|484|551|519|533|518|479|539|542|522|588|556|553|566|563|515|505|563|545|550|545|520|513|512|531|493|505|521|472|493|472|513|493|500|484|468|488|463|489|459|462|454|448|443|472|436|431|395|436|402|407|430|431|375|447|433|438|389|419|376|460|449|378|451|419|408|407|394|402|407|421|406|381|414|410|405|409|400|426|468|390|426|415|436|445|418|424|391|397|462|443|434|412|461|445|489|466|471|467|477|428|481|439|469|486|475|492|487|491|495|535|474|493|503|547|570|551|578|555|561|599|563|617|635|627|654|593|654|639|621|675|672|685|723|764|793|815|774|794|822|864|839|956|957|1046|1095|1132|1181|1238|1331|1441|1483|1663|1774|1929|2094|2427|2684|2957|3470|3840|4334|5100|5710|6426|7018|8050|8536|9378|9892|10110|10283|10486|9727|8783|7680|6476|5142|3918|4403</HistCounts>
      </HistItem>
    </Histograms>
    <Metadata domain="IMAGE_STRUCTURE">
      <MDI key="COMPRESSION">JPEG</MDI>
    </Metadata>
    <Metadata>
      <MDI key="BandName">Band_2</MDI>
      <MDI key="SourceBandIndex">1</MDI>
      <MDI key="STATISTICS_COVARIANCES">3360.734593814732,3598.980689481637,3898.85710606221</MDI>
      <MDI key="STATISTICS_EXCLUDEDVALUES"></MDI>
      <MDI key="STATISTICS_MAXIMUM">255</MDI>
      <MDI key="STATISTICS_MEAN">207.14158630371</MDI>
      <MDI key="STATISTICS_MINIMUM">0</MDI>
      <MDI key="STATISTICS_SKIPFACTORX">1</MDI>
      <MDI key="STATISTICS_SKIPFACTORY">1</MDI>
      <MDI key="STATISTICS_STDDEV">59.991505144326</MDI>
    </Metadata>
  </PAMRasterBand>
  <PAMRasterBand band="3">
    <NoDataValue>2.56000000000000E+02</NoDataValue>
    <Histograms>
      <HistItem>
        <HistMin>-0.5</HistMin>
        <HistMax>255.5</HistMax>
        <BucketCount>256</BucketCount>
        <IncludeOutOfRange>1</IncludeOutOfRange>
        <Approximate>0</Approximate>
        <HistCounts>654|72|64|69|59|65|76|55|62|75|64|73|71|69|82|62|75|87|82|95|91|82|90|126|118|130|147|181|158|175|193|190|205|219|200|267|246|240|277|290|309|303|355|331|372|407|396|430|487|487|465|525|520|536|554|624|593|609|573|588|633|644|577|597|603|609|549|599|556|559|554|556|537|476|517|467|476|478|463|483|475|491|470|432|436|445|401|443|449|431|421|451|415|392|422|427|407|429|401|385|390|422|417|410|399|375|391|380|393|373|391|391|414|384|378|360|430|360|391|387|350|363|376|391|365|380|388|363|395|421|394|387|359|405|400|393|385|360|364|369|362|384|350|403|372|417|411|380|398|413|399|405|410|398|404|432|412|364|377|413|403|433|416|418|435|457|383|453|452|457|455|476|472|453|452|441|473|419|464|479|494|485|502|552|524|483|550|512|537|546|545|546|553|588|578|644|644|639|607|619|621|615|661|666|728|696|665|719|737|795|796|840|823|915|904|931|984|1098|1009|1102|1145|1233|1204|1404|1421|1522|1742|1715|1962|2181|2485|2665|2951|3356|3725|4312|4931|5341|6156|6786|7374|7935|8483|9097|9254|9404|9490|8817|8360|7431|6618|5554|3654|3594|1599|2895</HistCounts>
      </HistItem>
    </Histograms>
    <Metadata domain="IMAGE_STRUCTURE">
      <MDI key="COMPRESSION">JPEG</MDI>
    </Metadata>
    <Metadata>
      <MDI key="BandName">Band_3</MDI>
      <MDI key="SourceBandIndex">2</MDI>
      <MDI key="STATISTICS_COVARIANCES">3755.224683021293,3898.85710606221,4261.876812915703</MDI>
      <MDI key="STATISTICS_EXCLUDEDVALUES"></MDI>
      <MDI key="STATISTICS_MAXIMUM">255</MDI>
      <MDI key="STATISTICS_MEAN">201.15843963623</MDI>
      <MDI key="STATISTICS_MINIMUM">0</MDI>
      <MDI key="STATISTICS_SKIPFACTORX">1</MDI>
      <MDI key="STATISTICS_SKIPFACTORY">1</MDI>
      <MDI key="STATISTICS_STDDEV">65.283051498193</MDI>
    </Metadata>
  </PAMRasterBand>
</PAMDataset>
