<PAMDataset>
  <SRS>GEOGCS["GCS_WGS_1984",DATUM["WGS_1984",SPHEROID["WGS_84",6378137.0,298.257223563,AUTHORITY["EPSG","7030"]],AUTHORITY["EPSG","6326"]],PRIMEM["Greenwich",0.0,AUTHORITY["EPSG","8901"]],UNIT["Degree",0.0174532925199433,AUTHORITY["EPSG","9102"]],AUTHORITY["EPSG","4326"]]</SRS>
  <Metadata domain="IMAGE_STRUCTURE">
    <MDI key="COMPRESSION">JPEG</MDI>
    <MDI key="INTERLEAVE">PIXEL</MDI>
    <MDI key="SOURCE_COLOR_SPACE">YCbCr</MDI>
  </Metadata>
  <Metadata>
    <MDI key="DataType">Generic</MDI>
  </Metadata>
  <Metadata domain="Esri">
    <MDI key="PyramidResamplingType">NEAREST</MDI>
  </Metadata>
  <PAMRasterBand band="1">
    <NoDataValue>2.56000000000000E+02</NoDataValue>
    <Histograms>
      <HistItem>
        <HistMin>-0.5</HistMin>
        <HistMax>255.5</HistMax>
        <BucketCount>256</BucketCount>
        <IncludeOutOfRange>1</IncludeOutOfRange>
        <Approximate>0</Approximate>
        <HistCounts>0|1|0|1|1|1|1|0|8|2|7|8|5|13|13|9|10|23|14|33|37|53|49|48|72|58|88|83|81|100|129|129|156|149|174|151|193|174|205|210|228|242|239|265|271|301|292|335|307|332|400|364|354|397|400|431|422|432|452|464|473|436|479|471|510|460|502|549|472|511|535|474|500|533|578|535|490|534|481|494|516|498|476|507|487|494|473|459|459|450|445|492|477|414|418|420|410|437|422|432|392|370|391|390|371|430|369|366|385|371|362|358|403|387|395|386|349|374|361|387|373|406|370|357|372|355|349|396|381|370|375|385|403|367|385|369|378|377|402|393|412|429|374|379|384|423|398|384|368|404|417|421|396|405|420|435|422|417|420|443|425|433|412|411|427|429|433|448|449|453|469|466|423|476|464|470|467|479|442|502|489|451|497|529|545|519|531|562|508|551|528|581|606|612|607|619|648|564|645|685|616|657|681|650|689|737|715|727|723|771|832|821|799|838|839|885|844|924|901|984|961|925|920|1051|1038|1062|1158|1132|1227|1256|1350|1329|1401|1463|1569|1713|1903|2079|2367|2712|3116|3604|4208|5239|6149|7400|8612|9730|10825|11665|12104|12006|11278|10009|8457|21307</HistCounts>
      </HistItem>
    </Histograms>
    <Metadata domain="IMAGE_STRUCTURE">
      <MDI key="COMPRESSION">JPEG</MDI>
    </Metadata>
    <Metadata>
      <MDI key="BandName">Band_1</MDI>
      <MDI key="SourceBandIndex">0</MDI>
      <MDI key="STATISTICS_COVARIANCES">3836.876087842246,3551.039043129185,4167.347148322754</MDI>
      <MDI key="STATISTICS_EXCLUDEDVALUES"></MDI>
      <MDI key="STATISTICS_MAXIMUM">255</MDI>
      <MDI key="STATISTICS_MEAN">209.334690094</MDI>
      <MDI key="STATISTICS_MINIMUM">1</MDI>
      <MDI key="STATISTICS_SKIPFACTORX">1</MDI>
      <MDI key="STATISTICS_SKIPFACTORY">1</MDI>
      <MDI key="STATISTICS_STDDEV">61.942522453015</MDI>
    </Metadata>
  </PAMRasterBand>
  <PAMRasterBand band="2">
    <NoDataValue>2.56000000000000E+02</NoDataValue>
    <Histograms>
      <HistItem>
        <HistMin>-0.5</HistMin>
        <HistMax>255.5</HistMax>
        <BucketCount>256</BucketCount>
        <IncludeOutOfRange>1</IncludeOutOfRange>
        <Approximate>0</Approximate>
        <HistCounts>174|40|40|46|55|56|49|52|70|69|53|56|58|67|76|60|55|50|61|58|64|75|57|65|67|63|62|48|65|48|47|63|87|68|71|71|58|93|86|100|105|86|119|118|129|137|141|171|178|186|184|200|218|241|280|287|307|339|354|391|404|428|444|497|558|544|583|587|626|644|654|694|737|689|758|755|743|767|715|799|770|740|844|778|769|795|789|768|754|729|736|742|702|703|710|667|632|623|618|586|587|598|559|600|558|577|504|510|517|541|483|465|496|475|483|456|469|431|469|462|461|448|492|412|430|468|444|469|461|434|403|445|412|439|412|407|466|427|449|434|438|398|399|435|434|442|427|438|438|377|447|444|423|428|418|424|447|460|482|460|400|427|444|480|456|473|443|480|488|435|478|479|489|468|460|499|485|497|488|476|489|518|515|510|495|505|523|549|493|554|539|567|529|546|595|583|587|566|648|564|603|672|615|678|620|737|717|702|719|744|726|744|775|796|865|864|876|882|898|997|1015|1012|1105|1240|1246|1321|1430|1506|1626|1806|1894|2146|2357|2652|2980|3299|3808|4160|4761|5435|6179|6840|7804|8435|9171|9661|10028|10203|9912|9374|8386|6985|5626|4132|2929|2663</HistCounts>
      </HistItem>
    </Histograms>
    <Metadata domain="IMAGE_STRUCTURE">
      <MDI key="COMPRESSION">JPEG</MDI>
    </Metadata>
    <Metadata>
      <MDI key="BandName">Band_2</MDI>
      <MDI key="SourceBandIndex">1</MDI>
      <MDI key="STATISTICS_COVARIANCES">3551.039043129185,3969.312773472005,4515.301700544038</MDI>
      <MDI key="STATISTICS_EXCLUDEDVALUES"></MDI>
      <MDI key="STATISTICS_MAXIMUM">255</MDI>
      <MDI key="STATISTICS_MEAN">201.87380599975</MDI>
      <MDI key="STATISTICS_MINIMUM">0</MDI>
      <MDI key="STATISTICS_SKIPFACTORX">1</MDI>
      <MDI key="STATISTICS_SKIPFACTORY">1</MDI>
      <MDI key="STATISTICS_STDDEV">63.00248228024</MDI>
    </Metadata>
  </PAMRasterBand>
  <PAMRasterBand band="3">
    <NoDataValue>2.56000000000000E+02</NoDataValue>
    <Histograms>
      <HistItem>
        <HistMin>-0.5</HistMin>
        <HistMax>255.5</HistMax>
        <BucketCount>256</BucketCount>
        <IncludeOutOfRange>1</IncludeOutOfRange>
        <Approximate>0</Approximate>
        <HistCounts>818|108|123|139|122|119|159|153|189|192|207|227|228|217|265|271|234|268|296|299|361|377|353|360|396|392|422|401|358|406|458|460|479|477|513|476|523|538|529|524|548|559|554|532|532|561|542|570|609|581|599|568|659|626|663|649|644|613|668|613|669|668|659|664|661|599|634|616|605|600|571|580|539|528|568|516|541|536|490|455|482|454|474|441|440|458|467|440|414|415|385|379|423|380|377|443|382|374|363|414|381|377|404|375|375|416|419|378|352|362|420|388|347|416|366|329|397|388|370|413|411|379|392|392|387|379|423|390|413|373|420|412|387|341|386|413|413|408|417|390|437|407|406|415|407|423|401|385|430|388|415|419|458|395|407|452|398|441|426|424|459|448|458|444|432|496|491|447|500|465|521|473|502|460|472|471|515|508|504|491|530|547|561|538|542|517|577|605|583|593|624|589|607|652|624|632|628|667|669|695|667|739|708|759|732|780|809|826|828|904|922|924|976|1034|976|1064|1169|1103|1222|1270|1266|1487|1518|1634|1648|1854|1936|2213|2321|2548|2756|3097|3370|3732|4168|4608|5007|5683|6107|6827|7203|7819|7859|8368|8245|8059|7708|7037|6324|5266|4399|3525|2222|2090|975|1952</HistCounts>
      </HistItem>
    </Histograms>
    <Metadata domain="IMAGE_STRUCTURE">
      <MDI key="COMPRESSION">JPEG</MDI>
    </Metadata>
    <Metadata>
      <MDI key="BandName">Band_3</MDI>
      <MDI key="SourceBandIndex">2</MDI>
      <MDI key="STATISTICS_COVARIANCES">4167.347148322754,4515.301700544038,5211.302250174334</MDI>
      <MDI key="STATISTICS_EXCLUDEDVALUES"></MDI>
      <MDI key="STATISTICS_MAXIMUM">255</MDI>
      <MDI key="STATISTICS_MEAN">190.86081695556</MDI>
      <MDI key="STATISTICS_MINIMUM">0</MDI>
      <MDI key="STATISTICS_SKIPFACTORX">1</MDI>
      <MDI key="STATISTICS_SKIPFACTORY">1</MDI>
      <MDI key="STATISTICS_STDDEV">72.189349977502</MDI>
    </Metadata>
  </PAMRasterBand>
</PAMDataset>
